packaged_non_std/__init__.py
packaged_non_std/ingest_data.py
packaged_non_std/score.py
packaged_non_std/train.py
packaged_non_std_sai.bandaru-0.0.1.dist-info/METADATA
packaged_non_std_sai.bandaru-0.0.1.dist-info/WHEEL
packaged_non_std_sai.bandaru-0.0.1.dist-info/top_level.txt
packaged_non_std_sai.bandaru-0.0.1.dist-info/RECORD
