Metadata-Version: 2.1
Name: packaged_non_std__sai.bandaru
Version: 0.0.1
Summary: A custom package for the House Price Prediction project
Author-email: Sai Krishna Dattu Bandaru <sai.bandaru@tigeranalytics.com>
Classifier: Programming Language :: Python :: 3
Classifier: Operating System :: OS Independent
Requires-Python: >=3.9
